MANIFEST.in
README.rst
buildout.cfg
develop.cfg
requirements.txt
setup.py
version.txt
bob/__init__.py
bob.bio.caffe_face.egg-info/PKG-INFO
bob.bio.caffe_face.egg-info/SOURCES.txt
bob.bio.caffe_face.egg-info/dependency_links.txt
bob.bio.caffe_face.egg-info/entry_points.txt
bob.bio.caffe_face.egg-info/not-zip-safe
bob.bio.caffe_face.egg-info/requires.txt
bob.bio.caffe_face.egg-info/top_level.txt
bob/bio/__init__.py
bob/bio/caffe_face/__init__.py
bob/bio/caffe_face/config/__init__.py
bob/bio/caffe_face/config/extractor/__init__.py
bob/bio/caffe_face/config/extractor/lightcnn.py
bob/bio/caffe_face/config/extractor/vgg_features.py
bob/bio/caffe_face/config/preprocessor/__init__.py
bob/bio/caffe_face/config/preprocessor/lightcnn_preprocessor.py
bob/bio/caffe_face/config/preprocessor/vgg_preprocessor.py
bob/bio/caffe_face/extractor/LightCNNExtractor.py
bob/bio/caffe_face/extractor/__init__.py
bob/bio/caffe_face/extractor/vgg_features.py
bob/bio/caffe_face/test/__init__.py
bob/bio/caffe_face/test/test_extractors.py
doc/conf.py
doc/implementation.rst
doc/implemented.rst
doc/index.rst