Metadata-Version: 1.1
Name: bob.bio.caffe-face
Version: 1.1.3
Summary: Face Feature extraction using caffe pre-trained models
Home-page: https://gitlab.idiap.ch/bob/bob.bio.caffe_face
Author: Tiago de Freitas Pereira
Author-email: tiago.pereira@idiap.ch
License: BSD
Keywords: bob,biometric recognition,evaluation
Platform: UNKNOWN
Classifier: Framework :: Bob
Classifier: Development Status :: 4 - Beta
Classifier: Intended Audience :: Developers
Classifier: License :: OSI Approved :: BSD License
Classifier: Natural Language :: English
Classifier: Programming Language :: Python
Classifier: Topic :: Scientific/Engineering :: Artificial Intelligence
